eventy/__init__.py
eventy/context/__init__.py
eventy/context/eventy_context.py
eventy/logging/__init__.py
eventy/logging/context_filters.py
eventy/logging/gke_handler.py
eventy/logging/simple_handler.py
eventy/messaging/__init__.py
eventy/messaging/base.py
eventy/messaging/messaging_errors.py
eventy/messaging/transactional.py
eventy/messaging/kafka/__init__.py
eventy/messaging/kafka/kafka_admin.py
eventy/messaging/kafka/kafka_base.py
eventy/messaging/kafka/kafka_errors.py
eventy/messaging/kafka/kafka_transactional.py
eventy/record/__init__.py
eventy/record/event.py
eventy/record/record.py
eventy/record/record_errors.py
eventy/record/request.py
eventy/record/response.py
eventy/serialization/__init__.py
eventy/serialization/record_serializer.py
eventy/serialization/serialization_errors.py
eventy/serialization/avro/__init__.py
eventy/serialization/avro/avro_serializer.py
eventy/serialization/json/__init__.py
eventy/serialization/json/json_serializer.py
eventy3-3.0.0.dist-info/METADATA
eventy3-3.0.0.dist-info/WHEEL
eventy3-3.0.0.dist-info/top_level.txt
eventy3-3.0.0.dist-info/RECORD
