Metadata-Version: 2.1
Name: eventy3
Version: 3.0.0
Summary: Qotto/eventy
Home-page: https://gitlab.com/qotto/oss/eventy
Author: Qotto dev team
Author-email: dev@qotto.net
License: UNKNOWN
Platform: UNKNOWN
Classifier: Development Status :: 3 - Alpha
Classifier: Intended Audience :: Developers
Classifier: License :: OSI Approved :: MIT License
Classifier: Programming Language :: Python :: 3
Classifier: Programming Language :: Python :: 3.9
Requires-Python: >=3.7
Requires-Dist: coloredlogs (==15.0.1)
Requires-Dist: confluent-kafka (==1.7.0)
Requires-Dist: contextvars (==2.4)
Requires-Dist: humanfriendly (==9.2)
Requires-Dist: immutables (==0.15)
Requires-Dist: semver (==2.13.0)
Requires-Dist: urnparse (==0.2.0)
Provides-Extra: dev
